evolutionary_search/__init__.py
evolutionary_search/cv.py
evolutionary_search/optimize.py
sklearn_deap2-0.2.2.dist-info/DESCRIPTION.rst
sklearn_deap2-0.2.2.dist-info/METADATA
sklearn_deap2-0.2.2.dist-info/RECORD
sklearn_deap2-0.2.2.dist-info/WHEEL
sklearn_deap2-0.2.2.dist-info/metadata.json
sklearn_deap2-0.2.2.dist-info/top_level.txt
