Metadata-Version: 2.0
Name: sklearn-deap2
Version: 0.2.2
Summary: Use evolutionary algorithms instead of gridsearch in scikit-learn.
Home-page: https://github.com/ClimbsRocks/sklearn-deap
Author: Rodrigo
Author-email: UNKNOWN
License: UNKNOWN
Platform: UNKNOWN
Classifier: Development Status :: 4 - Beta
Classifier: Programming Language :: Python :: 2
Classifier: Programming Language :: Python :: 2.6
Classifier: Programming Language :: Python :: 2.7
Classifier: Programming Language :: Python :: 3
Classifier: Programming Language :: Python :: 3.3
Classifier: Programming Language :: Python :: 3.4
Classifier: Programming Language :: Python
Classifier: Intended Audience :: Science/Research
Classifier: Intended Audience :: Developers
Requires-Dist: deap (>=1.0.2)
Requires-Dist: numpy (>=1.9.3)
Requires-Dist: scikit-learn (>=0.18.0)
Requires-Dist: scipy (>=0.14.0)
